LICENSE.md
README.md
pyproject.toml
setup.py
gym/__init__.py
gym/core.py
gym/error.py
gym/logger.py
gym/py.typed
gym/version.py
gym.egg-info/PKG-INFO
gym.egg-info/SOURCES.txt
gym.egg-info/dependency_links.txt
gym.egg-info/not-zip-safe
gym.egg-info/requires.txt
gym.egg-info/top_level.txt
gym/envs/__init__.py
gym/envs/registration.py
gym/envs/box2d/__init__.py
gym/envs/box2d/bipedal_walker.py
gym/envs/box2d/car_dynamics.py
gym/envs/box2d/car_racing.py
gym/envs/box2d/lunar_lander.py
gym/envs/classic_control/__init__.py
gym/envs/classic_control/acrobot.py
gym/envs/classic_control/cartpole.py
gym/envs/classic_control/continuous_mountain_car.py
gym/envs/classic_control/mountain_car.py
gym/envs/classic_control/pendulum.py
gym/envs/classic_control/utils.py
gym/envs/classic_control/assets/clockwise.png
gym/envs/mujoco/__init__.py
gym/envs/mujoco/ant.py
gym/envs/mujoco/ant_v3.py
gym/envs/mujoco/ant_v4.py
gym/envs/mujoco/half_cheetah.py
gym/envs/mujoco/half_cheetah_v3.py
gym/envs/mujoco/half_cheetah_v4.py
gym/envs/mujoco/hopper.py
gym/envs/mujoco/hopper_v3.py
gym/envs/mujoco/hopper_v4.py
gym/envs/mujoco/humanoid.py
gym/envs/mujoco/humanoid_v3.py
gym/envs/mujoco/humanoid_v4.py
gym/envs/mujoco/humanoidstandup.py
gym/envs/mujoco/humanoidstandup_v4.py
gym/envs/mujoco/inverted_double_pendulum.py
gym/envs/mujoco/inverted_double_pendulum_v4.py
gym/envs/mujoco/inverted_pendulum.py
gym/envs/mujoco/inverted_pendulum_v4.py
gym/envs/mujoco/mujoco_env.py
gym/envs/mujoco/mujoco_rendering.py
gym/envs/mujoco/pusher.py
gym/envs/mujoco/pusher_v4.py
gym/envs/mujoco/reacher.py
gym/envs/mujoco/reacher_v4.py
gym/envs/mujoco/swimmer.py
gym/envs/mujoco/swimmer_v3.py
gym/envs/mujoco/swimmer_v4.py
gym/envs/mujoco/walker2d.py
gym/envs/mujoco/walker2d_v3.py
gym/envs/mujoco/walker2d_v4.py
gym/envs/mujoco/assets/ant.xml
gym/envs/mujoco/assets/half_cheetah.xml
gym/envs/mujoco/assets/hopper.xml
gym/envs/mujoco/assets/humanoid.xml
gym/envs/mujoco/assets/humanoidstandup.xml
gym/envs/mujoco/assets/inverted_double_pendulum.xml
gym/envs/mujoco/assets/inverted_pendulum.xml
gym/envs/mujoco/assets/point.xml
gym/envs/mujoco/assets/pusher.xml
