Metadata-Version: 2.1
Name: gym
Version: 0.26.1
Summary: Gym: A universal API for reinforcement learning environments
Home-page: https://www.gymlibrary.dev/
Author: Gym Community
Author-email: jkterry@umd.edu
License: MIT
Platform: UNKNOWN
Classifier: Programming Language :: Python :: 3
Classifier: Programming Language :: Python :: 3.6
Classifier: Programming Language :: Python :: 3.7
Classifier: Programming Language :: Python :: 3.8
Classifier: Programming Language :: Python :: 3.9
Classifier: Programming Language :: Python :: 3.10
Requires-Python: >=3.6
Provides-Extra: atari
Provides-Extra: accept-rom-license
Provides-Extra: box2d
Provides-Extra: classic_control
Provides-Extra: mujoco_py
Provides-Extra: mujoco
Provides-Extra: toy_text
Provides-Extra: other
Provides-Extra: testing
Provides-Extra: all
License-File: LICENSE.md
